odoo/addons/hr_contract_currency/README.rst
odoo/addons/hr_contract_currency/__init__.py
odoo/addons/hr_contract_currency/__manifest__.py
odoo/addons/hr_contract_currency/i18n/es_PA.po
odoo/addons/hr_contract_currency/i18n/fr.po
odoo/addons/hr_contract_currency/i18n/hr_contract_currency.pot
odoo/addons/hr_contract_currency/i18n/it.po
odoo/addons/hr_contract_currency/models/__init__.py
odoo/addons/hr_contract_currency/models/hr_contract.py
odoo/addons/hr_contract_currency/readme/CONTRIBUTORS.rst
odoo/addons/hr_contract_currency/readme/DESCRIPTION.rst
odoo/addons/hr_contract_currency/static/description/icon.png
odoo/addons/hr_contract_currency/static/description/index.html
odoo/addons/hr_contract_currency/tests/__init__.py
odoo/addons/hr_contract_currency/tests/test_hr_contract_currency.py
odoo/addons/hr_contract_currency/views/hr_contract.xml
odoo13_addon_hr_contract_currency-13.0.1.0.1.dev13.dist-info/METADATA
odoo13_addon_hr_contract_currency-13.0.1.0.1.dev13.dist-info/WHEEL
odoo13_addon_hr_contract_currency-13.0.1.0.1.dev13.dist-info/top_level.txt
odoo13_addon_hr_contract_currency-13.0.1.0.1.dev13.dist-info/RECORD
